ghmsi_text_select/__init__.py
ghmsi_text_select/example.py
ghmsi_text_select/frontend/build/asset-manifest.json
ghmsi_text_select/frontend/build/bootstrap.min.css
ghmsi_text_select/frontend/build/index.html
ghmsi_text_select/frontend/build/static/js/main.5f81757d.js
ghmsi_text_select/frontend/build/static/js/main.5f81757d.js.LICENSE.txt
ghmsi_text_select/frontend/build/static/js/main.5f81757d.js.map
ghmsi_text_select/frontend/node_modules/flatted/python/flatted.py
ghmsi_text_select/frontend/node_modules/shell-quote/print.py
ghmsi_text_select-0.0.7.dist-info/licenses/LICENSE
ghmsi_text_select-0.0.7.dist-info/METADATA
ghmsi_text_select-0.0.7.dist-info/WHEEL
ghmsi_text_select-0.0.7.dist-info/top_level.txt
ghmsi_text_select-0.0.7.dist-info/RECORD
